{"skeleton":{"hash":"W9r3r6X96XbfrehB5RTyE40fGT4","spine":"2.1.27","width":2072,"height":1004},"bones":[{"name":"root"}],"slots":[{"name":"C_Lvcaodi_1","bone":"root","attachment":"C_Lvcaodi_1"},{"name":"C_Lvcaodi_2","bone":"root","attachment":"C_Lvcaodi_2"},{"name":"C_Lvcaodi_3","bone":"root","attachment":"C_Lvcaodi_3"}],"skins":{"default":{"C_Lvcaodi_1":{"C_Lvcaodi_1":{"x":356,"y":375,"width":720,"height":1004}},"C_Lvcaodi_2":{"C_Lvcaodi_2":{"x":1072,"y":375,"width":720,"height":1004}},"C_Lvcaodi_3":{"C_Lvcaodi_3":{"x":1748,"y":375,"width":640,"height":1004}}}},"animations":{"animation":{}}}